{
  "type": "Feature",
  "properties": {
    "gn:admin1_code":"02",
    "gn:admin2_code":"10297424",
    "gn:asciiname":"Vai'anae",
    "gn:country_code":"PF",
    "gn:dem":21,
    "gn:feature_class":"P",
    "gn:feature_code":"PPL",
    "gn:name":"Vai'anae",
    "gn:population":0,
    "gn:timezone":"Pacific/Tahiti",
    "iso:country":"PF",
    "wof:name":"Vai'anae",
    "wof:placetype":"locality"
},
  "geometry": {"coordinates":[-149.84974,-17.58299],"type":"Point"}
}