{
  "type": "Feature",
  "properties": {
    "gn:country":"PF",
    "gn:fcode":"PPL",
    "gn:population":237,
    "iso:country":"PF",
    "name:ceb_x_preferred":[
        "Amaru"
    ],
    "name:eng_x_preferred":[
        "Amaru"
    ],
    "name:fra_x_preferred":[
        "Amaru"
    ],
    "name:spa_x_preferred":[
        "Amaru"
    ],
    "name:tah_x_preferred":[
        "Amaru"
    ],
    "qs:name":"Amaru",
    "qs:photos_9r":0,
    "qs:photos_sr":0,
    "qs:pop_sr":"2",
    "wd:wordcount":132,
    "wof:name":"Amaru",
    "wof:placetype":"locality",
    "wof:population":237
},
  "geometry": {"coordinates":[-152.79283000000001,-22.64659],"type":"Point"}
}