{
  "type": "Feature",
  "properties": {
    "gn:admin1_code":"00",
    "gn:asciiname":"Hanamiai",
    "gn:country_code":"PF",
    "gn:dem":27,
    "gn:feature_class":"P",
    "gn:feature_code":"PPL",
    "gn:name":"Hanamiai",
    "gn:population":0,
    "gn:timezone":"Pacific/Marquesas",
    "iso:country":"PF",
    "wof:name":"Hanamiai",
    "wof:placetype":"locality"
},
  "geometry": {"coordinates":[-139.11134999999999,-9.94169],"type":"Point"}
}