{
  "type": "Feature",
  "properties": {
    "gn:admin1_code":"00",
    "gn:asciiname":"Faauanu",
    "gn:country_code":"PF",
    "gn:dem":-9999,
    "gn:feature_class":"P",
    "gn:feature_code":"PPL",
    "gn:name":"Faauanu",
    "gn:population":0,
    "gn:timezone":"Pacific/Tahiti",
    "iso:country":"PF",
    "wof:name":"Faauanu",
    "wof:placetype":"locality"
},
  "geometry": {"coordinates":[-149.34999999999999,-17.53333],"type":"Point"}
}