{
  "type": "Feature",
  "properties": {
    "gn:asciiname":"Paeua",
    "gn:country_code":"PF",
    "gn:dem":7,
    "gn:feature_class":"P",
    "gn:feature_code":"PPL",
    "gn:name":"Paeua",
    "gn:population":0,
    "gn:timezone":"Pacific/Tahiti",
    "iso:country":"PF",
    "wof:name":"Paeua",
    "wof:placetype":"locality"
},
  "geometry": {"coordinates":[-146.05172999999999,-14.4641],"type":"Point"}
}