{
  "type": "Feature",
  "properties": {
    "gn:country":"PF",
    "gn:fcode":"PPL",
    "gn:pop":486,
    "iso:country":"PF",
    "name:bul_x_preferred":[
        "\u0420\u0430\u0438\u0440\u0443\u0430"
    ],
    "name:eng_x_preferred":[
        "Rairua"
    ],
    "name:eng_x_variant":[
        "Rairoa"
    ],
    "name:fra_x_preferred":[
        "Rairua"
    ],
    "name:spa_x_preferred":[
        "Rairua"
    ],
    "name:tah_x_preferred":[
        "Rairua"
    ],
    "name:unk_x_variant":[
        "Raiurua"
    ],
    "qs:name":"Rairua",
    "qs:photos_9r":0,
    "qs:photos_sr":0,
    "qs:pop_sr":"2",
    "wof:name":"Rairua",
    "wof:placetype":"locality",
    "wof:population":486
},
  "geometry": {"coordinates":[-147.68333000000001,-23.86667],"type":"Point"}
}