{
  "type": "Feature",
  "properties": {
    "gn:admin1_code":"00",
    "gn:asciiname":"Tupapati",
    "gn:country_code":"PF",
    "gn:dem":7,
    "gn:feature_class":"P",
    "gn:feature_code":"PPL",
    "gn:name":"Tupapati",
    "gn:population":0,
    "gn:timezone":"Pacific/Tahiti",
    "iso:country":"PF",
    "wof:name":"Tupapati",
    "wof:placetype":"locality"
},
  "geometry": {"coordinates":[-142.66871,-17.54584],"type":"Point"}
}