{
  "type": "Feature",
  "properties": {
    "gn:asciiname":"Tumukuru",
    "gn:country_code":"PF",
    "gn:dem":10,
    "gn:feature_class":"P",
    "gn:feature_code":"PPLL",
    "gn:name":"Tumukuru",
    "gn:population":0,
    "gn:timezone":"Pacific/Tahiti",
    "iso:country":"PF",
    "wof:name":"Tumukuru",
    "wof:placetype":"locality"
},
  "geometry": {"coordinates":[-138.45014,-17.34548],"type":"Point"}
}