{
  "type": "Feature",
  "properties": {
    "gn:admin1_code":"00",
    "gn:asciiname":"Fareeru",
    "gn:country_code":"PF",
    "gn:dem":110,
    "gn:feature_class":"P",
    "gn:feature_code":"PPL",
    "gn:name":"Fareeru",
    "gn:population":0,
    "gn:timezone":"Pacific/Tahiti",
    "iso:country":"PF",
    "wof:name":"Fareeru",
    "wof:placetype":"locality"
},
  "geometry": {"coordinates":[-150.96614,-16.7653],"type":"Point"}
}