{
  "type": "Feature",
  "properties": {
    "gn:admin1_code":"00",
    "gn:asciiname":"Nairiri",
    "gn:country_code":"PF",
    "gn:dem":101,
    "gn:feature_class":"P",
    "gn:feature_code":"PPL",
    "gn:name":"Nairiri",
    "gn:population":0,
    "gn:timezone":"Pacific/Tahiti",
    "iso:country":"PF",
    "wof:name":"Nairiri",
    "wof:placetype":"locality"
},
  "geometry": {"coordinates":[-149.43333000000001,-17.76667],"type":"Point"}
}