{
  "type": "Feature",
  "properties": {
    "gn:admin1_code":"03",
    "gn:asciiname":"Tupana",
    "gn:country_code":"PF",
    "gn:dem":7,
    "gn:feature_class":"P",
    "gn:feature_code":"PPL",
    "gn:name":"Tupana",
    "gn:population":0,
    "gn:timezone":"Pacific/Tahiti",
    "iso:country":"PF",
    "wof:name":"Tupana",
    "wof:placetype":"locality"
},
  "geometry": {"coordinates":[-146.33333000000005,-16.13332999999999],"type":"Point"}
}