{
  "type": "Feature",
  "properties": {
    "gn:admin1_code":"00",
    "gn:asciiname":"Gahutu Tenohu",
    "gn:country_code":"PF",
    "gn:dem":28,
    "gn:feature_class":"P",
    "gn:feature_code":"PPL",
    "gn:name":"Gahutu Tenohu",
    "gn:population":0,
    "gn:timezone":"Pacific/Gambier",
    "iso:country":"PF",
    "wof:name":"Gahutu Tenohu",
    "wof:placetype":"locality"
},
  "geometry": {"coordinates":[-134.94443999999999,-23.075],"type":"Point"}
}