{
  "type": "Feature",
  "properties": {
    "gn:admin1_code":"00",
    "gn:asciiname":"Atituiti",
    "gn:cc2":"PF",
    "gn:country_code":"PF",
    "gn:dem":160,
    "gn:feature_class":"P",
    "gn:feature_code":"PPL",
    "gn:name":"Atituiti",
    "gn:population":0,
    "gn:timezone":"Pacific/Gambier",
    "iso:country":"PF",
    "name:und_x_variant":[
        "Atitouiti",
        "Atituiti"
    ],
    "wof:name":"Atituiti",
    "wof:placetype":"locality"
},
  "geometry": {"coordinates":[-134.97443999999999,-23.13056],"type":"Point"}
}