{
  "type": "Feature",
  "properties": {
    "gn:country":"PF",
    "gn:fcode":"PPL",
    "gn:pop":2842,
    "iso:country":"PF",
    "name:unk_x_variant":[
        "Toahotu"
    ],
    "qs:name":"Tohautu",
    "qs:photos_9r":0,
    "qs:photos_sr":0,
    "qs:pop_sr":"4",
    "wof:name":"Tohautu",
    "wof:placetype":"locality",
    "wof:population":2842
},
  "geometry": {"coordinates":[-149.31666999999999,-17.75],"type":"Point"}
}