{
  "type": "Feature",
  "properties": {
    "gn:admin1_code":"00",
    "gn:asciiname":"Gataha",
    "gn:country_code":"PF",
    "gn:dem":6,
    "gn:feature_class":"P",
    "gn:feature_code":"PPL",
    "gn:name":"Gataha",
    "gn:population":0,
    "gn:timezone":"Pacific/Gambier",
    "iso:country":"PF",
    "wof:name":"Gataha",
    "wof:placetype":"locality"
},
  "geometry": {"coordinates":[-134.95139,-23.08528],"type":"Point"}
}