{
  "type": "Feature",
  "properties": {
    "gn:admin1_code":"00",
    "gn:asciiname":"Mahanatoa",
    "gn:country_code":"PF",
    "gn:dem":118,
    "gn:feature_class":"P",
    "gn:feature_code":"PPL",
    "gn:name":"Mahanatoa",
    "gn:population":0,
    "gn:timezone":"Pacific/Tahiti",
    "iso:country":"PF",
    "wof:name":"Mahanatoa",
    "wof:placetype":"locality"
},
  "geometry": {"coordinates":[-147.66666999999995,-23.86667000000001],"type":"Point"}
}