{
  "type": "Feature",
  "properties": {
    "gn:admin1_code":"00",
    "gn:asciiname":"Taiokai",
    "gn:country_code":"PF",
    "gn:dem":-9999,
    "gn:feature_class":"P",
    "gn:feature_code":"PPL",
    "gn:name":"Taiokai",
    "gn:population":0,
    "gn:timezone":"Pacific/Marquesas",
    "iso:country":"PF",
    "wof:name":"Taiokai",
    "wof:placetype":"locality"
},
  "geometry": {"coordinates":[-138.68611000000001,-10.43248],"type":"Point"}
}