{
  "type": "Feature",
  "properties": {
    "gn:admin1_code":"00",
    "gn:asciiname":"Mitirapa",
    "gn:country_code":"PF",
    "gn:dem":129,
    "gn:feature_class":"P",
    "gn:feature_code":"PPL",
    "gn:name":"Mitirapa",
    "gn:population":0,
    "gn:timezone":"Pacific/Tahiti",
    "iso:country":"PF",
    "wof:name":"Mitirapa",
    "wof:placetype":"locality"
},
  "geometry": {"coordinates":[-149.26572999999999,-17.74682],"type":"Point"}
}