{
  "type": "Feature",
  "properties": {
    "gn:admin1_code":"00",
    "gn:asciiname":"Faanoa",
    "gn:country_code":"PF",
    "gn:dem":20,
    "gn:feature_class":"P",
    "gn:feature_code":"PPL",
    "gn:name":"Faanoa",
    "gn:population":0,
    "gn:timezone":"Pacific/Tahiti",
    "iso:country":"PF",
    "wof:name":"Faanoa",
    "wof:placetype":"locality"
},
  "geometry": {"coordinates":[-152.26667,-16.45],"type":"Point"}
}