{
  "type": "Feature",
  "properties": {
    "iso:country":"PF",
    "name:afr_x_preferred":[
        "Teahupoo"
    ],
    "name:bul_x_preferred":[
        "\u0422\u0435\u0430\u0445\u0443\u043f\u043e"
    ],
    "name:deu_x_preferred":[
        "Teahupoo"
    ],
    "name:eng_x_preferred":[
        "Teahupo'o"
    ],
    "name:fra_x_preferred":[
        "Teahupoo"
    ],
    "name:lit_x_preferred":[
        "Teahupoo"
    ],
    "name:nld_x_preferred":[
        "Teahupo'o"
    ],
    "name:nob_x_preferred":[
        "Teahupoo"
    ],
    "name:nor_x_preferred":[
        "Teahupoo"
    ],
    "name:por_x_preferred":[
        "Teahupo'o"
    ],
    "name:rus_x_preferred":[
        "\u0422\u0435\u0430\u0445\u0443\u043f\u043e\u043e"
    ],
    "name:spa_x_preferred":[
        "Teahupo'o"
    ],
    "name:ukr_x_preferred":[
        "Teahupoo"
    ],
    "name:unk_x_variant":[
        "Teahupu"
    ],
    "qs:gn_country":"PF",
    "qs:gn_fcode":"PPL",
    "qs:gn_pop":1422,
    "qs:name":"Teahupoo",
    "qs:name_adm0":"Polyn\u00e9sie Fran\u00e7aise",
    "qs:name_adm1":"\u00celes du Vent",
    "qs:photos":0,
    "qs:photos_1k":0,
    "qs:photos_9k":0,
    "qs:photos_9r":0,
    "qs:photos_all":0,
    "qs:photos_sr":0,
    "qs:placetype":"Town",
    "qs:pop_sr":"3",
    "qs:woe_adm0":23424817,
    "wd:wordcount":973,
    "wof:name":"Teahupoo",
    "wof:placetype":"locality",
    "wof:population":1422
},
  "geometry": {"coordinates":[-149.26667,-17.83333],"type":"Point"}
}