{
  "type": "Feature",
  "properties": {
    "gn:admin1_code":"00",
    "gn:asciiname":"Auorotini",
    "gn:country_code":"PF",
    "gn:dem":-9999,
    "gn:feature_class":"P",
    "gn:feature_code":"PPL",
    "gn:name":"Auorotini",
    "gn:population":0,
    "gn:timezone":"Pacific/Gambier",
    "iso:country":"PF",
    "wof:name":"Auorotini",
    "wof:placetype":"locality"
},
  "geometry": {"coordinates":[-135.63333,-21.48333],"type":"Point"}
}