{
  "type": "Feature",
  "properties": {
    "gn:admin1_code":"03",
    "gn:asciiname":"Toini",
    "gn:country_code":"PF",
    "gn:dem":4,
    "gn:feature_class":"P",
    "gn:feature_code":"PPL",
    "gn:name":"Toini",
    "gn:population":0,
    "gn:timezone":"Pacific/Tahiti",
    "iso:country":"PF",
    "name:fin_x_preferred":[
        "Toini"
    ],
    "name:swe_x_preferred":[
        "Toini"
    ],
    "wof:name":"Toini",
    "wof:placetype":"locality"
},
  "geometry": {"coordinates":[-144.35645,-16.36618],"type":"Point"}
}