{
  "type": "Feature",
  "properties": {
    "gn:admin1_code":"00",
    "gn:asciiname":"Faatautia",
    "gn:country_code":"PF",
    "gn:dem":209,
    "gn:feature_class":"P",
    "gn:feature_code":"PPL",
    "gn:name":"Faatautia",
    "gn:population":0,
    "gn:timezone":"Pacific/Tahiti",
    "iso:country":"PF",
    "wof:name":"Faatautia",
    "wof:placetype":"locality"
},
  "geometry": {"coordinates":[-149.31666999999999,-17.63332999999999],"type":"Point"}
}