{
  "type": "Feature",
  "properties": {
    "gn:admin1_code":"03",
    "gn:admin2_code":"10295215",
    "gn:asciiname":"Tukuhora",
    "gn:cc2":"PF",
    "gn:country_code":"PF",
    "gn:dem":9,
    "gn:feature_class":"P",
    "gn:feature_code":"PPL",
    "gn:name":"Tukuhora",
    "gn:population":0,
    "gn:timezone":"Pacific/Tahiti",
    "iso:country":"PF",
    "name:rus_x_preferred":[
        "\u0422\u0443\u043a\u0443\u0445\u043e\u0440\u0430"
    ],
    "name:und_x_variant":[
        "Tuuhora",
        "Tukuhora"
    ],
    "wof:name":"Tukuhora",
    "wof:placetype":"locality"
},
  "geometry": {"coordinates":[-145.51709,-17.34605],"type":"Point"}
}