{
  "type": "Feature",
  "properties": {
    "gn:admin1_code":"02",
    "gn:asciiname":"Maeva",
    "gn:country_code":"PF",
    "gn:dem":55,
    "gn:feature_class":"P",
    "gn:feature_code":"PPL",
    "gn:name":"Maeva",
    "gn:population":0,
    "gn:timezone":"Pacific/Tahiti",
    "iso:country":"PF",
    "name:fra_x_preferred":[
        "Maeva"
    ],
    "name:und_x_variant":[
        "Moheva",
        "Maheva"
    ],
    "wof:name":"Maeva",
    "wof:placetype":"locality"
},
  "geometry": {"coordinates":[-150.9888,-16.70037],"type":"Point"}
}