{
  "type": "Feature",
  "properties": {
    "gn:admin1_code":"00",
    "gn:asciiname":"Otuofai",
    "gn:cc2":"PF",
    "gn:country_code":"PF",
    "gn:dem":60,
    "gn:feature_class":"P",
    "gn:feature_code":"PPL",
    "gn:name":"Otuofai",
    "gn:population":0,
    "gn:timezone":"Pacific/Tahiti",
    "iso:country":"PF",
    "name:und_x_variant":[
        "Utaofai",
        "Utuofai",
        "Otuofai"
    ],
    "wof:name":"Otuofai",
    "wof:placetype":"locality"
},
  "geometry": {"coordinates":[-149.31666999999999,-17.65],"type":"Point"}
}