{
  "type": "Feature",
  "properties": {
    "gn:admin1_code":"00",
    "gn:asciiname":"Matotea",
    "gn:country_code":"PF",
    "gn:dem":-9999,
    "gn:feature_class":"P",
    "gn:feature_code":"PPL",
    "gn:name":"Matotea",
    "gn:population":0,
    "gn:timezone":"Pacific/Tahiti",
    "iso:country":"PF",
    "wof:name":"Matotea",
    "wof:placetype":"locality"
},
  "geometry": {"coordinates":[-147.69999999999999,-23.88333],"type":"Point"}
}