{
  "type": "Feature",
  "properties": {
    "gn:admin1_code":"00",
    "gn:asciiname":"Fetuna",
    "gn:country_code":"PF",
    "gn:dem":37,
    "gn:feature_class":"P",
    "gn:feature_code":"PPL",
    "gn:name":"Fetuna",
    "gn:population":0,
    "gn:timezone":"Pacific/Tahiti",
    "iso:country":"PF",
    "wof:name":"Fetuna",
    "wof:placetype":"locality"
},
  "geometry": {"coordinates":[-151.43582000000001,-16.89609],"type":"Point"}
}