{
  "type": "Feature",
  "properties": {
    "gn:admin1_code":"00",
    "gn:asciiname":"Temao",
    "gn:country_code":"PF",
    "gn:dem":69,
    "gn:feature_class":"P",
    "gn:feature_code":"PPL",
    "gn:name":"Temao",
    "gn:population":0,
    "gn:timezone":"Pacific/Tahiti",
    "iso:country":"PF",
    "wof:name":"Temao",
    "wof:placetype":"locality"
},
  "geometry": {"coordinates":[-148.26667,-15.81667],"type":"Point"}
}