{
  "type": "Feature",
  "properties": {
    "gn:admin1_code":"00",
    "gn:asciiname":"Iumaru",
    "gn:country_code":"PF",
    "gn:dem":16,
    "gn:feature_class":"P",
    "gn:feature_code":"PPL",
    "gn:name":"Iumaru",
    "gn:population":0,
    "gn:timezone":"Pacific/Tahiti",
    "iso:country":"PF",
    "wof:name":"Iumaru",
    "wof:placetype":"locality"
},
  "geometry": {"coordinates":[-149.90000000000001,-17.53333],"type":"Point"}
}