{
  "type": "Feature",
  "properties": {
    "iso:country":"PF",
    "name:bul_x_preferred":[
        "\u0424\u0438\u0442\u0438"
    ],
    "name:ceb_x_preferred":[
        "Fitii"
    ],
    "name:eng_x_preferred":[
        "Fitii"
    ],
    "name:fra_x_preferred":[
        "Fitii"
    ],
    "name:spa_x_preferred":[
        "Fitii"
    ],
    "qs:gn_country":"PF",
    "qs:gn_fcode":"PPL",
    "qs:gn_pop":1154,
    "qs:name":"Fitii",
    "qs:name_adm0":"Polyn\u00e9sie Fran\u00e7aise",
    "qs:name_adm1":"\u00celes sous le Vent",
    "qs:photos":229,
    "qs:photos_1k":46,
    "qs:photos_9k":1,
    "qs:photos_9r":4,
    "qs:photos_all":229,
    "qs:photos_sr":4,
    "qs:placetype":"Town",
    "qs:pop_sr":"3",
    "qs:woe_adm0":23424817,
    "wof:name":"Fitii",
    "wof:placetype":"locality",
    "wof:population":1154
},
  "geometry": {"coordinates":[-151.03333000000001,-16.73333],"type":"Point"}
}