{
  "type": "Feature",
  "properties": {
    "gn:admin1_code":"00",
    "gn:asciiname":"Hanga Haa",
    "gn:country_code":"PF",
    "gn:dem":42,
    "gn:feature_class":"P",
    "gn:feature_code":"PPL",
    "gn:name":"Hanga Haa",
    "gn:population":0,
    "gn:timezone":"Pacific/Marquesas",
    "iso:country":"PF",
    "wof:name":"Hanga Haa",
    "wof:placetype":"locality"
},
  "geometry": {"coordinates":[-140.04383999999999,-8.87841],"type":"Point"}
}